pythermoai/__init__.py
pythermoai/app.py
pythermoai/agents/__init__.py
pythermoai/agents/config.py
pythermoai/agents/main.py
pythermoai/agents/mcp_manager.py
pythermoai/agents/prompts.py
pythermoai/agents/symbols.py
pythermoai/agents/thermo_agent.py
pythermoai/api/__init__.py
pythermoai/api/ai_api.py
pythermoai/api/config_api.py
pythermoai/api/data_agent.py
pythermoai/api/deps.py
pythermoai/api/equations_agent.py
pythermoai/api/llm.py
pythermoai/api/main.py
pythermoai/config/__init__.py
pythermoai/config/constants.py
pythermoai/config/settings.py
pythermoai/errors/__init__.py
pythermoai/llms/__init__.py
pythermoai/llms/llm_models.py
pythermoai/memory/__init__.py
pythermoai/memory/config_memory.py
pythermoai/models/__init__.py
pythermoai/models/api.py
pythermoai/models/chat.py
pythermoai/models/llm.py
pythermoai/models/mcp.py
pythermoai/ui/3rdpartylicenses.txt
pythermoai/ui/prerendered-routes.json
pythermoai/ui/browser/favicon.ico
pythermoai/ui/browser/index.html
pythermoai/ui/browser/main-GDRK36GS.js
pythermoai/ui/browser/styles-XP544DDI.css
pythermoai/ui/browser/assets/image/logo-1.ico
pythermoai/ui/browser/assets/image/logo1.png
pythermoai/ui/browser/assets/image/logo2.png
pythermoai/ui/browser/assets/image/mozichem.png
pythermoai/utils/__init__.py
pythermoai/utils/loader.py
pythermoai/utils/message_manager.py
pythermoai-0.1.2.dist-info/licenses/LICENSE
pythermoai-0.1.2.dist-info/METADATA
pythermoai-0.1.2.dist-info/WHEEL
pythermoai-0.1.2.dist-info/top_level.txt
pythermoai-0.1.2.dist-info/RECORD
