Metadata-Version: 2.4
Name: pythermoai
Version: 0.1.2
Summary: PyThermoAI is a Python package that leverages intelligent agents to search the web for thermodynamic data and equations, and seamlessly integrates the results into PyThermoDB.
Author-email: Sina Gilassi <sina.gilassi@gmail.com>
License-Expression: Apache-2.0
Project-URL: Homepage, https://github.com/sinagilassi/PyThermoAI
Classifier: Programming Language :: Python :: 3.11
Classifier: Operating System :: OS Independent
Requires-Python: >=3.11
License-File: LICENSE
Requires-Dist: fastapi[standard]>=0.115.14
Requires-Dist: langchain>=0.3.27
Requires-Dist: langgraph>=0.6.4
Requires-Dist: langsmith>=0.4.13
Requires-Dist: langchain-mcp-adapters>=0.1.8
Requires-Dist: langchain-anthropic>=0.3.18
Requires-Dist: langchain-google-genai>=2.1.9
Requires-Dist: langchain-openai>=0.3.29
Requires-Dist: langchain-xai>=0.2.5
Requires-Dist: pydantic>=2.11.7
Requires-Dist: pydantic-settings>=2.10.1
Requires-Dist: websockets>=15.0.1
Requires-Dist: python-dotenv
Requires-Dist: rich
Dynamic: license-file
